jodit/__init__.py
jodit/apps.py
jodit/configs.py
jodit/fields.py
jodit/settings.py
jodit/widgets.py
jodit/static/jodit/jodit-init.js
jodit/static/jodit/jodit.min.css
jodit/static/jodit/jodit.min.js
jodit/templates/jodit/widget.html
django_jodit-0.1.0.dist-info/METADATA
django_jodit-0.1.0.dist-info/WHEEL
django_jodit-0.1.0.dist-info/licenses/LICENSE
django_jodit-0.1.0.dist-info/RECORD
