Metadata-Version: 2.4
Name: django-jodit
Version: 0.1.0
Summary: A Django app to integrate Jodit WYSIWYG editor with support for admin and forms
Project-URL: Homepage, https://github.com/mounirmesselmeni/django-jodit
Project-URL: Repository, https://github.com/mounirmesselmeni/django-jodit
Author-email: Mounir Messelmeni <messelmeni.mounir@gmail.com>
License-Expression: MIT
License-File: LICENSE
Keywords: django,editor,html editor,jodit,rich text,wysiwyg
Classifier: Development Status :: 4 - Beta
Classifier: Environment :: Web Environment
Classifier: Framework :: Django
Classifier: Framework :: Django :: 4.2
Classifier: Framework :: Django :: 5.0
Classifier: Framework :: Django :: 5.1
Classifier: Framework :: Django :: 5.2
Classifier: Intended Audience :: Developers
Classifier: License :: OSI Approved :: MIT License
Classifier: Operating System :: OS Independent
Classifier: Programming Language :: Python
Classifier: Programming Language :: Python :: 3
Classifier: Programming Language :: Python :: 3.11
Classifier: Programming Language :: Python :: 3.12
Classifier: Programming Language :: Python :: 3.13
Classifier: Topic :: Software Development :: Libraries :: Python Modules
Requires-Python: >=3.10
Requires-Dist: django>=4.2
